phylogenetics/__init__.py
phylogenetics/__version__.py
phylogenetics/project.py
phylogenetics/project2.py
phylogenetics/tree.py
phylogenetics/dat/MtZoa.dat
phylogenetics/dat/cpREV10.dat
phylogenetics/dat/cpREV64.dat
phylogenetics/dat/dayhoff-dcmut.dat
phylogenetics/dat/dayhoff.dat
phylogenetics/dat/g1974a.dat
phylogenetics/dat/g1974c.dat
phylogenetics/dat/g1974p.dat
phylogenetics/dat/g1974v.dat
phylogenetics/dat/grantham.dat
phylogenetics/dat/jones-dcmut.dat
phylogenetics/dat/jones.dat
phylogenetics/dat/lg.dat
phylogenetics/dat/miyata.dat
phylogenetics/dat/mtArt.dat
phylogenetics/dat/mtREV24.dat
phylogenetics/dat/mtmam.dat
phylogenetics/dat/wag.dat
phylogenetics-0.5.0.dist-info/METADATA
phylogenetics-0.5.0.dist-info/RECORD
phylogenetics-0.5.0.dist-info/WHEEL
phylogenetics-0.5.0.dist-info/top_level.txt
