Metadata-Version: 2.1
Name: phylogenetics
Version: 0.5.0
Summary: Python API for managing a phylogenetics project
Home-page: https://github.com/Zsailer/phylogenetics
Author: Zachary Sailer
Author-email: zachsailer@gmail.com
License: MIT
Platform: UNKNOWN
Classifier: License :: OSI Approved :: MIT License
Classifier: Programming Language :: Python
Classifier: Programming Language :: Python :: 3
Classifier: Programming Language :: Python :: 3.6
Classifier: Programming Language :: Python :: Implementation :: CPython
Classifier: Programming Language :: Python :: Implementation :: PyPy
Requires-Python: >=3.6.0
